MANIFEST.in
setup.cfg
setup.py
pyf/__init__.py
pyf.services.egg-info/PKG-INFO
pyf.services.egg-info/SOURCES.txt
pyf.services.egg-info/dependency_links.txt
pyf.services.egg-info/entry_points.txt
pyf.services.egg-info/namespace_packages.txt
pyf.services.egg-info/not-zip-safe
pyf.services.egg-info/paster_plugins.txt
pyf.services.egg-info/requires.txt
pyf.services.egg-info/top_level.txt
pyf/services/__init__.py
pyf/services/websetup.py
pyf/services/config/__init__.py
pyf/services/config/app_cfg.py
pyf/services/config/environment.py
pyf/services/config/middleware.py
pyf/services/controllers/__init__.py
pyf/services/controllers/crud.py
pyf/services/controllers/descriptor.py
pyf/services/controllers/dispatch.py
pyf/services/controllers/error.py
pyf/services/controllers/events.py
pyf/services/controllers/root.py
pyf/services/controllers/tasks.py
pyf/services/controllers/template.py
pyf/services/controllers/tube.py
pyf/services/controllers/tubelayer.py
pyf/services/controllers/tubestorage.py
pyf/services/controllers/user.py
pyf/services/controllers/utils.py
pyf/services/controllers/widgets.py
pyf/services/core/__init__.py
pyf/services/core/docs.py
pyf/services/core/env.py
pyf/services/core/events.py
pyf/services/core/modifiers.py
pyf/services/core/password.py
pyf/services/core/router.py
pyf/services/core/station.py
pyf/services/core/storage.py
pyf/services/core/tasks.py
pyf/services/lib/__init__.py
pyf/services/lib/app_globals.py
pyf/services/lib/base.py
pyf/services/lib/helpers.py
pyf/services/migration/__init__.py
pyf/services/migration/manage.py
pyf/services/migration/versions/001_improved_messages.py
pyf/services/migration/versions/002_increase_payload_size.py
pyf/services/migration/versions/003_dispatcher_name.py
pyf/services/migration/versions/__init__.py
pyf/services/model/__init__.py
pyf/services/model/auth.py
pyf/services/model/events.py
pyf/services/model/main.py
pyf/services/model/tasks.py
pyf/services/public/favicon.ico
pyf/services/public/css/bubbles.css
pyf/services/public/css/design.css
pyf/services/public/css/design_pythoncolors.css
pyf/services/public/css/design_xmlcolors.css
pyf/services/public/css/js-graph-it.css
pyf/services/public/css/pagination.css
pyf/services/public/css/progress.css
pyf/services/public/css/pythoncolors.css
pyf/services/public/css/style.css
