Metadata-Version: 1.0
Name: pyf.services
Version: 2.0.2
Summary: PyF Services is a web service, web-based IDE and scheduler for flow-based programming part of the PyF Framework.
Home-page: http://pyfproject.org
Author: htaieb, jonathan schemoul
Author-email: he.taieb@gmail.com, jonathan.schemoul@gmail.com
License: UNKNOWN
Platform: UNKNOWN
